galgek_ukp_nomousauto_grivind/__init__.py
galgek_ukp_nomousauto_grivind/data_conversion.py
galgek_ukp_nomousauto_grivind/model.py
galgek_ukp_nomousauto_grivind/train_setup.py
galgek_ukp_nomousauto_grivind-0.1.6.dist-info/LICENSE
galgek_ukp_nomousauto_grivind-0.1.6.dist-info/METADATA
galgek_ukp_nomousauto_grivind-0.1.6.dist-info/WHEEL
galgek_ukp_nomousauto_grivind-0.1.6.dist-info/top_level.txt
galgek_ukp_nomousauto_grivind-0.1.6.dist-info/RECORD
