Metadata-Version: 2.1
Name: galgek-ukp-nomousauto-grivind
Version: 0.1.6
Summary: Decription
Home-page: http://github.com/kshamruk/galgek-ukp-nomousauto-grivind
Author: kshamruk
Author-email: c.shamruk@gmail.com
License: MIT
Platform: UNKNOWN
Classifier: Programming Language :: Python :: 3
Classifier: License :: OSI Approved :: MIT License
Classifier: Operating System :: OS Independent
Requires-Python: >=3.6
Requires-Dist: scipy
Requires-Dist: numpy
Requires-Dist: opencv-python
Requires-Dist: torch
Requires-Dist: numba
Requires-Dist: efficientnet-pytorch
Requires-Dist: tqdm
